chatbot_encodedmind/__init__.py
chatbot_encodedmind/ai_client.py
chatbot_encodedmind/audio_io.py
chatbot_encodedmind/core.py
chatbot_encodedmind-1.0.6.dist-info/METADATA
chatbot_encodedmind-1.0.6.dist-info/WHEEL
chatbot_encodedmind-1.0.6.dist-info/entry_points.txt
chatbot_encodedmind-1.0.6.dist-info/RECORD
