Metadata-Version: 2.4
Name: chatbot_encodedmind
Version: 1.0.6
Summary: Voice-based AI chatbot powered by OpenAI
Project-URL: Homepage, https://github.com/EncodedMind/Chatbot
Project-URL: Documentation, https://github.com/EncodedMind/Chatbot#readme
Project-URL: Bug Tracker, https://github.com/EncodedMind/Chatbot/issues
Project-URL: Changelog, https://github.com/EncodedMind/Chatbot/blob/main/CHANGELOG.md
Author-email: Dimitris Andreakis <andreakisdimitrios@gmail.com>
License: MIT
Requires-Python: >=3.10
Requires-Dist: annotated-types==0.7.0
Requires-Dist: anyio==4.6.2.post1
Requires-Dist: certifi==2024.8.30
Requires-Dist: cffi==1.17.1
Requires-Dist: charset-normalizer==3.4.0
Requires-Dist: distro==1.9.0
Requires-Dist: exceptiongroup==1.2.2
Requires-Dist: h11==0.14.0
Requires-Dist: httpcore==1.0.6
Requires-Dist: httpx==0.27.2
Requires-Dist: idna==3.10
Requires-Dist: jiter==0.6.1
Requires-Dist: numpy==2.1.2
Requires-Dist: openai==1.52.1
Requires-Dist: pycparser==2.22
Requires-Dist: pydantic-core==2.23.4
Requires-Dist: pydantic==2.9.2
Requires-Dist: pydub==0.25.1
Requires-Dist: requests==2.32.3
Requires-Dist: scipy==1.14.1
Requires-Dist: sniffio==1.3.1
Requires-Dist: sounddevice==0.5.1
Requires-Dist: tqdm==4.66.5
Requires-Dist: typing-extensions==4.12.2
Requires-Dist: urllib3==2.2.3
